{
    "fermi_energy_dft": 10.8195,
    "temperature": 299.98637294316444,
    "number_of_electrons_exact": 8.0,
    "band_energy_dft_calculation": 39.36799551146591,
    "total_energy_dft_calculation": -214.6705028473946,
    "grid_dimensions": [
        24,
        24,
        36
    ],
    "electrons_per_atom": 4.0,
    "number_of_electrons_from_eigenvals": 7.999885482269594,
    "ibrav": 0,
    "ecutwfc": 40.0,
    "ecutrho": 160.0,
    "degauss": 0.0019,
    "pseudopotentials": {
        "Si": "Si.pz-vbc.UPF"
    },
    "entropy_contribution_dft_calculation": -0.0014428837439420731,
    "voxel": {
        "array": [
            [
                0.11196624626713857,
                0.0,
                0.0
            ],
            [
                -0.05598312313356928,
                0.09696556842349868,
                0.0
            ],
            [
                0.0,
                0.0,
                0.12757859571413585
            ]
        ]
    },
    "atoms": {
        "numbers": [
            14,
            14
        ],
        "positions": [
            [
                0.08454759358925361,
                1.6674190748636362,
                0.9198409607542681
            ],
            [
                1.2803105579395118,
                0.9869242383967675,
                3.3632957595975195
            ]
        ],
        "cell": [
            [
                2.6871899104113255,
                0.0,
                0.0
            ],
            [
                -1.3435949552056627,
                2.3271736421639684,
                0.0
            ],
            [
                0.0,
                0.0,
                4.59282944570889
            ]
        ],
        "pbc": [
            true,
            true,
            true
        ]
    }
}